[
  {
    "sessions": 4,
    "venues": 3,
    "sold": 18,
    "available": 925,
    "total": 943,
    "gross": 401.0,
    "max_gross": 23313.0,
    "occupancy": 1.91,
    "name": "BTS 2017 Live Trilogy EPISODE III THE WINGS TOUR THE FINAL Remastered",
    "summary": "BTS cemented their global status with their first Billboard Music Award win, and their meteoric rise is powerfully captured in <[BTS 2017 Live Trilogy EPISODE III THE WINGS TOUR THE FINAL Remastered>.",
    "duration": 107,
    "releaseDate": "2025-09-25T00:00:00",
    "posterImage": "mx/posters/au/2017-bts-the-wings-tour-one-sheet-artwork-english.jpg",
    "id": "HO00008076"
  },
  {
    "sessions": 1,
    "venues": 1,
    "sold": 0,
    "available": 476,
    "total": 476,
    "gross": 0.0,
    "max_gross": 12852.0,
    "occupancy": 0.0,
    "name": "Smurfs",
    "summary": "When Papa Smurf is mysteriously taken by evil wizards, Razamel and Gargamel, Smurfette leads the Smurfs on a mission into the real world to save him.",
    "duration": 92,
    "releaseDate": "2025-06-30T00:00:00",
    "posterImage": "mx/posters/nz/smurfs-ac57ccac.jpg",
    "id": "HO00007177"
  }
]