[
  {
    "id": 468578,
    "cinemaId": "1002",
    "movieId": "HO00007763",
    "date": "2025-09-14T12:30:00",
    "typeId": "XTREME",
    "screenName": "XTREMESCREEN",
    "operator": "SYL",
    "total": 1075,
    "sold": 0,
    "available": 1075,
    "occupancy": 0.0,
    "max_gross": 29025.0,
    "total_gross": 0.0,
    "price": 27.0,
    "error": false
  },
  {
    "id": 468580,
    "cinemaId": "1002",
    "movieId": "HO00007763",
    "date": "2025-09-14T13:50:00",
    "typeId": "STANDARD",
    "screenName": "Cinema 2",
    "operator": "SYL",
    "total": 726,
    "sold": 0,
    "available": 726,
    "occupancy": 0.0,
    "max_gross": 19602.0,
    "total_gross": 0.0,
    "price": 27.0,
    "error": false
  },
  {
    "id": 67304,
    "cinemaId": "ORMCIN",
    "movieId": "HO00007811",
    "date": "2025-09-14T18:10:00",
    "typeId": "XTREME",
    "screenName": "Xtremescreen 01",
    "operator": "ORM",
    "total": 286,
    "sold": 25,
    "available": 261,
    "occupancy": 8.74,
    "max_gross": 9295.0,
    "total_gross": 812.5,
    "price": 32.5,
    "error": false
  },
  {
    "id": 359062,
    "cinemaId": "1001",
    "movieId": "HO00008135",
    "date": "2025-09-14T13:10:00",
    "typeId": "STANDARD",
    "screenName": "Cinema 2",
    "operator": "WPK",
    "total": 76,
    "sold": 2,
    "available": 74,
    "occupancy": 2.63,
    "max_gross": 2052.0,
    "total_gross": 54.0,
    "price": 27.0,
    "error": false
  },
  {
    "id": 468579,
    "cinemaId": "1002",
    "movieId": "HO00007763",
    "date": "2025-09-14T12:30:00",
    "typeId": "LUX",
    "screenName": "HOYTS LUX 11",
    "operator": "SYLDS",
    "total": 96,
    "sold": 0,
    "available": 96,
    "occupancy": 0.0,
    "max_gross": 2592.0,
    "total_gross": 0.0,
    "price": 27.0,
    "error": false
  },
  {
    "id": 358771,
    "cinemaId": "1001",
    "movieId": "HO00007763",
    "date": "2025-09-14T10:00:00",
    "typeId": "STANDARD",
    "screenName": "Cinema 4",
    "operator": "WPK",
    "total": 114,
    "sold": 0,
    "available": 114,
    "occupancy": 0.0,
    "max_gross": 3078.0,
    "total_gross": 0.0,
    "price": 27.0,
    "error": false
  },
  {
    "id": 67306,
    "cinemaId": "ORMCIN",
    "movieId": "HO00007812",
    "date": "2025-09-14T15:00:00",
    "typeId": "STANDARD",
    "screenName": "Cinema 03",
    "operator": "ORM",
    "total": 120,
    "sold": 18,
    "available": 102,
    "occupancy": 15.0,
    "max_gross": 3360.0,
    "total_gross": 504.0,
    "price": 28.0,
    "error": false
  },
  {
    "id": 358171,
    "cinemaId": "1001",
    "movieId": "HO00007811",
    "date": "2025-09-14T18:00:00",
    "typeId": "STANDARD",
    "screenName": "Cinema 4",
    "operator": "WPK",
    "total": 114,
    "sold": 13,
    "available": 101,
    "occupancy": 11.4,
    "max_gross": 3192.0,
    "total_gross": 364.0,
    "price": 28.0,
    "error": false
  },
  {
    "id": 68214,
    "cinemaId": "ORMCIN",
    "movieId": "HO00008135",
    "date": "2025-09-14T10:30:00",
    "typeId": "STANDARD",
    "screenName": "Cinema 03",
    "operator": "ORM",
    "total": 120,
    "sold": 0,
    "available": 120,
    "occupancy": 0.0,
    "max_gross": 3240.0,
    "total_gross": 0.0,
    "price": 27.0,
    "error": false
  },
  {
    "id": 358773,
    "cinemaId": "1001",
    "movieId": "HO00007763",
    "date": "2025-09-14T15:50:00",
    "typeId": "STANDARD",
    "screenName": "Cinema 3",
    "operator": "WPK",
    "total": 126,
    "sold": 0,
    "available": 126,
    "occupancy": 0.0,
    "max_gross": 3402.0,
    "total_gross": 0.0,
    "price": 27.0,
    "error": false
  },
  {
    "id": 327268,
    "cinemaId": "1014",
    "movieId": "HO00007763",
    "date": "2025-09-14T13:00:00",
    "typeId": "LUX",
    "screenName": "HOYTS LUX 07",
    "operator": "TERLP",
    "total": 198,
    "sold": 0,
    "available": 198,
    "occupancy": 0.0,
    "max_gross": 5346.0,
    "total_gross": 0.0,
    "price": 27.0,
    "error": false
  },
  {
    "id": 327270,
    "cinemaId": "1014",
    "movieId": "HO00007763",
    "date": "2025-09-14T15:30:00",
    "typeId": "LUX",
    "screenName": "HOYTS LUX 07",
    "operator": "TERLP",
    "total": 198,
    "sold": 0,
    "available": 198,
    "occupancy": 0.0,
    "max_gross": 5346.0,
    "total_gross": 0.0,
    "price": 27.0,
    "error": false
  },
  {
    "id": 327259,
    "cinemaId": "1014",
    "movieId": "HO00008135",
    "date": "2025-09-14T14:30:00",
    "typeId": "STANDARD",
    "screenName": "Cinema 6",
    "operator": "TER",
    "total": 264,
    "sold": 1,
    "available": 263,
    "occupancy": 0.38,
    "max_gross": 7128.0,
    "total_gross": 27.0,
    "price": 27.0,
    "error": false
  },
  {
    "id": 468577,
    "cinemaId": "1002",
    "movieId": "HO00007763",
    "date": "2025-09-14T10:10:00",
    "typeId": "XTREME",
    "screenName": "XTREMESCREEN",
    "operator": "SYL",
    "total": 1075,
    "sold": 0,
    "available": 1075,
    "occupancy": 0.0,
    "max_gross": 29025.0,
    "total_gross": 0.0,
    "price": 27.0,
    "error": false
  },
  {
    "id": 327267,
    "cinemaId": "1014",
    "movieId": "HO00007763",
    "date": "2025-09-14T10:30:00",
    "typeId": "XTREME",
    "screenName": "Xtremescreen",
    "operator": "TER",
    "total": 484,
    "sold": 0,
    "available": 484,
    "occupancy": 0.0,
    "max_gross": 13068.0,
    "total_gross": 0.0,
    "price": 27.0,
    "error": false
  },
  {
    "id": 358170,
    "cinemaId": "1001",
    "movieId": "HO00007811",
    "date": "2025-09-14T14:40:00",
    "typeId": "STANDARD",
    "screenName": "Cinema 4",
    "operator": "WPK",
    "total": 114,
    "sold": 16,
    "available": 98,
    "occupancy": 14.04,
    "max_gross": 3192.0,
    "total_gross": 448.0,
    "price": 28.0,
    "error": false
  },
  {
    "id": 358770,
    "cinemaId": "1001",
    "movieId": "HO00007763",
    "date": "2025-09-14T12:20:00",
    "typeId": "STANDARD",
    "screenName": "Cinema 4",
    "operator": "WPK",
    "total": 114,
    "sold": 0,
    "available": 114,
    "occupancy": 0.0,
    "max_gross": 3078.0,
    "total_gross": 0.0,
    "price": 27.0,
    "error": false
  },
  {
    "id": 67305,
    "cinemaId": "ORMCIN",
    "movieId": "HO00007811",
    "date": "2025-09-14T21:30:00",
    "typeId": "XTREME",
    "screenName": "Xtremescreen 01",
    "operator": "ORM",
    "total": 286,
    "sold": 4,
    "available": 282,
    "occupancy": 1.4,
    "max_gross": 9295.0,
    "total_gross": 130.0,
    "price": 32.5,
    "error": false
  },
  {
    "id": 326142,
    "cinemaId": "1014",
    "movieId": "HO00007811",
    "date": "2025-09-14T18:00:00",
    "typeId": "LUX",
    "screenName": "HOYTS LUX 09",
    "operator": "TERLP",
    "total": 95,
    "sold": 10,
    "available": 85,
    "occupancy": 10.53,
    "max_gross": 2565.0,
    "total_gross": 270.0,
    "price": 27.0,
    "error": false
  },
  {
    "id": 358772,
    "cinemaId": "1001",
    "movieId": "HO00007763",
    "date": "2025-09-14T13:30:00",
    "typeId": "STANDARD",
    "screenName": "Cinema 3",
    "operator": "WPK",
    "total": 126,
    "sold": 0,
    "available": 126,
    "occupancy": 0.0,
    "max_gross": 3402.0,
    "total_gross": 0.0,
    "price": 27.0,
    "error": false
  },
  {
    "id": 79459,
    "cinemaId": "CHCCIN",
    "movieId": "HO00007763",
    "date": "2025-09-14T10:30:00",
    "typeId": "XTREME",
    "screenName": "Xtremescreen 04",
    "operator": "CHC",
    "total": 372,
    "sold": 0,
    "available": 372,
    "occupancy": 0.0,
    "max_gross": 10044.0,
    "total_gross": 0.0,
    "price": 27.0,
    "error": false
  },
  {
    "id": 79462,
    "cinemaId": "CHCCIN",
    "movieId": "HO00008135",
    "date": "2025-09-14T14:00:00",
    "typeId": "STANDARD",
    "screenName": "Cinema 02",
    "operator": "CHC",
    "total": 78,
    "sold": 7,
    "available": 71,
    "occupancy": 8.97,
    "max_gross": 2106.0,
    "total_gross": 189.0,
    "price": 27.0,
    "error": false,
    "last_error": "HTTP 500"
  },
  {
    "id": 467603,
    "cinemaId": "1002",
    "movieId": "HO00007812",
    "date": "2025-09-14T16:00:00",
    "typeId": "LUX",
    "screenName": "HOYTS LUX 14",
    "operator": "SYLDS",
    "total": 51,
    "sold": 6,
    "available": 45,
    "occupancy": 11.76,
    "max_gross": 1377.0,
    "total_gross": 162.0,
    "price": 27.0,
    "error": false,
    "last_error": "HTTP 500"
  },
  {
    "id": 467604,
    "cinemaId": "1002",
    "movieId": "HO00007812",
    "date": "2025-09-14T16:00:00",
    "typeId": "STANDARD",
    "screenName": "Cinema 4",
    "operator": "SYL",
    "total": 550,
    "sold": 12,
    "available": 538,
    "occupancy": 2.18,
    "max_gross": 15125.0,
    "total_gross": 330.0,
    "price": 27.5,
    "error": false
  },
  {
    "id": 275914,
    "cinemaId": "1004",
    "movieId": "HO00007763",
    "date": "2025-09-14T12:15:00",
    "typeId": "STANDARD",
    "screenName": "Cinema 4",
    "operator": "NTH",
    "total": 160,
    "sold": 0,
    "available": 160,
    "occupancy": 0.0,
    "max_gross": 4320.0,
    "total_gross": 0.0,
    "price": 27.0,
    "error": false
  },
  {
    "id": 327273,
    "cinemaId": "1014",
    "movieId": "HO00007763",
    "date": "2025-09-14T18:00:00",
    "typeId": "XTREME",
    "screenName": "Xtremescreen",
    "operator": "TER",
    "total": 484,
    "sold": 0,
    "available": 484,
    "occupancy": 0.0,
    "max_gross": 13068.0,
    "total_gross": 0.0,
    "price": 27.0,
    "error": false
  },
  {
    "id": 79807,
    "cinemaId": "CHCCIN",
    "movieId": "HO00007811",
    "date": "2025-09-14T21:00:00",
    "typeId": "LUX",
    "screenName": "HOYTS LUX 01",
    "operator": "CHCLP",
    "total": 45,
    "sold": 0,
    "available": 45,
    "occupancy": 0.0,
    "max_gross": 1215.0,
    "total_gross": 0.0,
    "price": 27.0,
    "error": false
  },
  {
    "id": 469031,
    "cinemaId": "1002",
    "movieId": "HO00008135",
    "date": "2025-09-14T13:00:00",
    "typeId": "STANDARD",
    "screenName": "Cinema 6",
    "operator": "SYL",
    "total": 198,
    "sold": 0,
    "available": 198,
    "occupancy": 0.0,
    "max_gross": 5346.0,
    "total_gross": 0.0,
    "price": 27.0,
    "error": false
  },
  {
    "id": 79461,
    "cinemaId": "CHCCIN",
    "movieId": "HO00007763",
    "date": "2025-09-14T15:30:00",
    "typeId": "XTREME",
    "screenName": "Xtremescreen 04",
    "operator": "CHC",
    "total": 372,
    "sold": 0,
    "available": 372,
    "occupancy": 0.0,
    "max_gross": 10044.0,
    "total_gross": 0.0,
    "price": 27.0,
    "error": false
  },
  {
    "id": 467605,
    "cinemaId": "1002",
    "movieId": "HO00007811",
    "date": "2025-09-14T10:00:00",
    "typeId": "STANDARD",
    "screenName": "Cinema 4",
    "operator": "SYL",
    "total": 550,
    "sold": 23,
    "available": 527,
    "occupancy": 4.18,
    "max_gross": 15125.0,
    "total_gross": 632.5,
    "price": 27.5,
    "error": false
  },
  {
    "id": 467607,
    "cinemaId": "1002",
    "movieId": "HO00007811",
    "date": "2025-09-14T14:50:00",
    "typeId": "XTREME",
    "screenName": "XTREMESCREEN",
    "operator": "SYL",
    "total": 1075,
    "sold": 6,
    "available": 1069,
    "occupancy": 0.56,
    "max_gross": 34400.0,
    "total_gross": 192.0,
    "price": 32.0,
    "error": false
  },
  {
    "id": 327272,
    "cinemaId": "1014",
    "movieId": "HO00007763",
    "date": "2025-09-14T18:00:00",
    "typeId": "LUX",
    "screenName": "HOYTS LUX 07",
    "operator": "TERLP",
    "total": 198,
    "sold": 0,
    "available": 198,
    "occupancy": 0.0,
    "max_gross": 5346.0,
    "total_gross": 0.0,
    "price": 27.0,
    "error": false
  },
  {
    "id": 468581,
    "cinemaId": "1002",
    "movieId": "HO00007763",
    "date": "2025-09-14T13:50:00",
    "typeId": "LUX",
    "screenName": "HOYTS LUX 12",
    "operator": "SYLDS",
    "total": 69,
    "sold": 0,
    "available": 69,
    "occupancy": 0.0,
    "max_gross": 1863.0,
    "total_gross": 0.0,
    "price": 27.0,
    "error": false
  },
  {
    "id": 327269,
    "cinemaId": "1014",
    "movieId": "HO00007763",
    "date": "2025-09-14T13:00:00",
    "typeId": "XTREME",
    "screenName": "Xtremescreen",
    "operator": "TER",
    "total": 484,
    "sold": 0,
    "available": 484,
    "occupancy": 0.0,
    "max_gross": 13068.0,
    "total_gross": 0.0,
    "price": 27.0,
    "error": false
  },
  {
    "id": 326143,
    "cinemaId": "1014",
    "movieId": "HO00007811",
    "date": "2025-09-14T18:00:00",
    "typeId": "STANDARD",
    "screenName": "Cinema 3",
    "operator": "TER",
    "total": 252,
    "sold": 7,
    "available": 245,
    "occupancy": 2.78,
    "max_gross": 6678.0,
    "total_gross": 185.5,
    "price": 26.5,
    "error": false
  },
  {
    "id": 327271,
    "cinemaId": "1014",
    "movieId": "HO00007763",
    "date": "2025-09-14T15:30:00",
    "typeId": "XTREME",
    "screenName": "Xtremescreen",
    "operator": "TER",
    "total": 484,
    "sold": 0,
    "available": 484,
    "occupancy": 0.0,
    "max_gross": 13068.0,
    "total_gross": 0.0,
    "price": 27.0,
    "error": false
  },
  {
    "id": 467608,
    "cinemaId": "1002",
    "movieId": "HO00007811",
    "date": "2025-09-14T18:10:00",
    "typeId": "LUX",
    "screenName": "HOYTS LUX 11",
    "operator": "SYLDS",
    "total": 96,
    "sold": 12,
    "available": 84,
    "occupancy": 12.5,
    "max_gross": 2592.0,
    "total_gross": 324.0,
    "price": 27.0,
    "error": false
  },
  {
    "id": 79049,
    "cinemaId": "CHCCIN",
    "movieId": "HO00007812",
    "date": "2025-09-14T16:00:00",
    "typeId": "STANDARD",
    "screenName": "Cinema 02",
    "operator": "CHC",
    "total": 78,
    "sold": 9,
    "available": 69,
    "occupancy": 11.54,
    "max_gross": 1599.0,
    "total_gross": 184.5,
    "price": 20.5,
    "error": false
  },
  {
    "id": 467609,
    "cinemaId": "1002",
    "movieId": "HO00007811",
    "date": "2025-09-14T18:10:00",
    "typeId": "XTREME",
    "screenName": "XTREMESCREEN",
    "operator": "SYL",
    "total": 1075,
    "sold": 2,
    "available": 1073,
    "occupancy": 0.19,
    "max_gross": 34400.0,
    "total_gross": 64.0,
    "price": 32.0,
    "error": false
  },
  {
    "id": 468582,
    "cinemaId": "1002",
    "movieId": "HO00007763",
    "date": "2025-09-14T16:10:00",
    "typeId": "STANDARD",
    "screenName": "Cinema 2",
    "operator": "SYL",
    "total": 726,
    "sold": 0,
    "available": 726,
    "occupancy": 0.0,
    "max_gross": 19602.0,
    "total_gross": 0.0,
    "price": 27.0,
    "error": false
  },
  {
    "id": 275423,
    "cinemaId": "1004",
    "movieId": "HO00007811",
    "date": "2025-09-14T16:00:00",
    "typeId": "STANDARD",
    "screenName": "Cinema 5",
    "operator": "NTH",
    "total": 108,
    "sold": 27,
    "available": 81,
    "occupancy": 25.0,
    "max_gross": 2214.0,
    "total_gross": 553.5,
    "price": 20.5,
    "error": false
  },
  {
    "id": 275916,
    "cinemaId": "1004",
    "movieId": "HO00007763",
    "date": "2025-09-14T16:30:00",
    "typeId": "STANDARD",
    "screenName": "Cinema 4",
    "operator": "NTH",
    "total": 160,
    "sold": 0,
    "available": 160,
    "occupancy": 0.0,
    "max_gross": 4320.0,
    "total_gross": 0.0,
    "price": 27.0,
    "error": false
  },
  {
    "id": 467606,
    "cinemaId": "1002",
    "movieId": "HO00007811",
    "date": "2025-09-14T14:50:00",
    "typeId": "LUX",
    "screenName": "HOYTS LUX 11",
    "operator": "SYLDS",
    "total": 96,
    "sold": 2,
    "available": 94,
    "occupancy": 2.08,
    "max_gross": 2592.0,
    "total_gross": 54.0,
    "price": 27.0,
    "error": false
  },
  {
    "id": 275913,
    "cinemaId": "1004",
    "movieId": "HO00007763",
    "date": "2025-09-14T10:00:00",
    "typeId": "STANDARD",
    "screenName": "Cinema 4",
    "operator": "NTH",
    "total": 160,
    "sold": 0,
    "available": 160,
    "occupancy": 0.0,
    "max_gross": 4320.0,
    "total_gross": 0.0,
    "price": 27.0,
    "error": false
  },
  {
    "id": 79460,
    "cinemaId": "CHCCIN",
    "movieId": "HO00007763",
    "date": "2025-09-14T13:00:00",
    "typeId": "XTREME",
    "screenName": "Xtremescreen 04",
    "operator": "CHC",
    "total": 372,
    "sold": 0,
    "available": 372,
    "occupancy": 0.0,
    "max_gross": 10044.0,
    "total_gross": 0.0,
    "price": 27.0,
    "error": false
  },
  {
    "id": 275424,
    "cinemaId": "1004",
    "movieId": "HO00007812",
    "date": "2025-09-14T18:00:00",
    "typeId": "STANDARD",
    "screenName": "Cinema 3",
    "operator": "NTH",
    "total": 118,
    "sold": 11,
    "available": 107,
    "occupancy": 9.32,
    "max_gross": 2419.0,
    "total_gross": 225.5,
    "price": 20.5,
    "error": false
  },
  {
    "id": 275918,
    "cinemaId": "1004",
    "movieId": "HO00008135",
    "date": "2025-09-14T14:00:00",
    "typeId": "STANDARD",
    "screenName": "Cinema 5",
    "operator": "NTH",
    "total": 108,
    "sold": 4,
    "available": 104,
    "occupancy": 3.7,
    "max_gross": 2916.0,
    "total_gross": 108.0,
    "price": 27.0,
    "error": false
  },
  {
    "id": 275917,
    "cinemaId": "1004",
    "movieId": "HO00007763",
    "date": "2025-09-14T19:00:00",
    "typeId": "STANDARD",
    "screenName": "Cinema 4",
    "operator": "NTH",
    "total": 160,
    "sold": 0,
    "available": 160,
    "occupancy": 0.0,
    "max_gross": 4320.0,
    "total_gross": 0.0,
    "price": 27.0,
    "error": false
  },
  {
    "id": 468583,
    "cinemaId": "1002",
    "movieId": "HO00007763",
    "date": "2025-09-14T16:10:00",
    "typeId": "LUX",
    "screenName": "HOYTS LUX 12",
    "operator": "SYLDS",
    "total": 69,
    "sold": 0,
    "available": 69,
    "occupancy": 0.0,
    "max_gross": 1863.0,
    "total_gross": 0.0,
    "price": 27.0,
    "error": false
  },
  {
    "id": 275915,
    "cinemaId": "1004",
    "movieId": "HO00007763",
    "date": "2025-09-14T14:30:00",
    "typeId": "STANDARD",
    "screenName": "Cinema 4",
    "operator": "NTH",
    "total": 160,
    "sold": 0,
    "available": 160,
    "occupancy": 0.0,
    "max_gross": 4320.0,
    "total_gross": 0.0,
    "price": 27.0,
    "error": false
  },
  {
    "id": 79050,
    "cinemaId": "CHCCIN",
    "movieId": "HO00007811",
    "date": "2025-09-14T18:00:00",
    "typeId": "XTREME",
    "screenName": "Xtremescreen 04",
    "operator": "CHC",
    "total": 372,
    "sold": 57,
    "available": 315,
    "occupancy": 15.32,
    "max_gross": 9300.0,
    "total_gross": 1425.0,
    "price": 25.0,
    "error": false
  },
  {
    "id": 177018,
    "cinemaId": "1013",
    "movieId": "HO00007763",
    "date": "2025-09-14T15:40:00",
    "typeId": "STANDARD",
    "screenName": "Cinema 2",
    "operator": "MIS",
    "total": 140,
    "sold": 0,
    "available": 140,
    "occupancy": 0.0,
    "max_gross": 3780.0,
    "total_gross": 0.0,
    "price": 27.0,
    "error": false
  },
  {
    "id": 176658,
    "cinemaId": "1013",
    "movieId": "HO00007811",
    "date": "2025-09-14T18:00:00",
    "typeId": "STANDARD",
    "screenName": "Cinema 1",
    "operator": "MIS",
    "total": 140,
    "sold": 0,
    "available": 140,
    "occupancy": 0.0,
    "max_gross": 3640.0,
    "total_gross": 0.0,
    "price": 26.0,
    "error": false
  },
  {
    "id": 177017,
    "cinemaId": "1013",
    "movieId": "HO00007763",
    "date": "2025-09-14T13:10:00",
    "typeId": "STANDARD",
    "screenName": "Cinema 2",
    "operator": "MIS",
    "total": 140,
    "sold": 0,
    "available": 140,
    "occupancy": 0.0,
    "max_gross": 3780.0,
    "total_gross": 0.0,
    "price": 27.0,
    "error": false
  },
  {
    "id": 399503,
    "cinemaId": "1012",
    "movieId": "HO00007763",
    "date": "2025-09-14T12:10:00",
    "typeId": "XTREME",
    "screenName": "Xtremescreen 1",
    "operator": "BOT",
    "total": 312,
    "sold": 0,
    "available": 312,
    "occupancy": 0.0,
    "max_gross": 8424.0,
    "total_gross": 0.0,
    "price": 27.0,
    "error": false
  },
  {
    "id": 399507,
    "cinemaId": "1012",
    "movieId": "HO00007763",
    "date": "2025-09-14T18:20:00",
    "typeId": "STANDARD",
    "screenName": "Cinema 2",
    "operator": "BOT",
    "total": 172,
    "sold": 0,
    "available": 172,
    "occupancy": 0.0,
    "max_gross": 4644.0,
    "total_gross": 0.0,
    "price": 27.0,
    "error": false
  },
  {
    "id": 398704,
    "cinemaId": "1012",
    "movieId": "HO00007811",
    "date": "2025-09-14T14:40:00",
    "typeId": "XTREME",
    "screenName": "Xtremescreen 1",
    "operator": "BOT",
    "total": 312,
    "sold": 30,
    "available": 282,
    "occupancy": 9.62,
    "max_gross": 10140.0,
    "total_gross": 975.0,
    "price": 32.5,
    "error": false
  },
  {
    "id": 168183,
    "cinemaId": "HAMCIN",
    "movieId": "HO00007811",
    "date": "2025-09-14T18:00:00",
    "typeId": "STANDARD",
    "screenName": "METRO 6",
    "operator": "HAM",
    "total": 42,
    "sold": 9,
    "available": 33,
    "occupancy": 21.43,
    "max_gross": 1113.0,
    "total_gross": 238.5,
    "price": 26.5,
    "error": false
  },
  {
    "id": 399501,
    "cinemaId": "1012",
    "movieId": "HO00007763",
    "date": "2025-09-14T09:40:00",
    "typeId": "XTREME",
    "screenName": "Xtremescreen 1",
    "operator": "BOT",
    "total": 312,
    "sold": 0,
    "available": 312,
    "occupancy": 0.0,
    "max_gross": 8424.0,
    "total_gross": 0.0,
    "price": 27.0,
    "error": false
  },
  {
    "id": 168181,
    "cinemaId": "HAMCIN",
    "movieId": "HO00007811",
    "date": "2025-09-14T10:00:00",
    "typeId": "STANDARD",
    "screenName": "METRO 2",
    "operator": "HAM",
    "total": 126,
    "sold": 0,
    "available": 126,
    "occupancy": 0.0,
    "max_gross": 2898.0,
    "total_gross": 0.0,
    "price": 23.0,
    "error": false
  },
  {
    "id": 398705,
    "cinemaId": "1012",
    "movieId": "HO00007811",
    "date": "2025-09-14T14:40:00",
    "typeId": "LUX",
    "screenName": "HOYTS LUX 01",
    "operator": "BOTLP",
    "total": 72,
    "sold": 11,
    "available": 61,
    "occupancy": 15.28,
    "max_gross": 1944.0,
    "total_gross": 297.0,
    "price": 27.0,
    "error": false
  },
  {
    "id": 177016,
    "cinemaId": "1013",
    "movieId": "HO00007763",
    "date": "2025-09-14T10:00:00",
    "typeId": "STANDARD",
    "screenName": "Cinema 1",
    "operator": "MIS",
    "total": 140,
    "sold": 0,
    "available": 140,
    "occupancy": 0.0,
    "max_gross": 3780.0,
    "total_gross": 0.0,
    "price": 27.0,
    "error": false
  },
  {
    "id": 177183,
    "cinemaId": "1013",
    "movieId": "HO00008135",
    "date": "2025-09-14T11:20:00",
    "typeId": "STANDARD",
    "screenName": "Cinema 4",
    "operator": "MIS",
    "total": 120,
    "sold": 0,
    "available": 120,
    "occupancy": 0.0,
    "max_gross": 3240.0,
    "total_gross": 0.0,
    "price": 27.0,
    "error": false
  },
  {
    "id": 176659,
    "cinemaId": "1013",
    "movieId": "HO00007812",
    "date": "2025-09-14T14:50:00",
    "typeId": "STANDARD",
    "screenName": "Cinema 1",
    "operator": "MIS",
    "total": 140,
    "sold": 2,
    "available": 138,
    "occupancy": 1.43,
    "max_gross": 3640.0,
    "total_gross": 52.0,
    "price": 26.0,
    "error": false
  },
  {
    "id": 168799,
    "cinemaId": "HAMCIN",
    "movieId": "HO00007763",
    "date": "2025-09-14T18:00:00",
    "typeId": "STANDARD",
    "screenName": "METRO 3",
    "operator": "HAM",
    "total": 209,
    "sold": 0,
    "available": 209,
    "occupancy": 0.0,
    "max_gross": 5643.0,
    "total_gross": 0.0,
    "price": 27.0,
    "error": false
  },
  {
    "id": 398702,
    "cinemaId": "1012",
    "movieId": "HO00007811",
    "date": "2025-09-14T18:00:00",
    "typeId": "XTREME",
    "screenName": "Xtremescreen 1",
    "operator": "BOT",
    "total": 312,
    "sold": 4,
    "available": 308,
    "occupancy": 1.28,
    "max_gross": 10140.0,
    "total_gross": 130.0,
    "price": 32.5,
    "error": false
  },
  {
    "id": 177015,
    "cinemaId": "1013",
    "movieId": "HO00007763",
    "date": "2025-09-14T12:20:00",
    "typeId": "STANDARD",
    "screenName": "Cinema 1",
    "operator": "MIS",
    "total": 140,
    "sold": 0,
    "available": 140,
    "occupancy": 0.0,
    "max_gross": 3780.0,
    "total_gross": 0.0,
    "price": 27.0,
    "error": false
  },
  {
    "id": 399508,
    "cinemaId": "1012",
    "movieId": "HO00007763",
    "date": "2025-09-14T13:40:00",
    "typeId": "STANDARD",
    "screenName": "Cinema 2",
    "operator": "BOT",
    "total": 172,
    "sold": 0,
    "available": 172,
    "occupancy": 0.0,
    "max_gross": 4644.0,
    "total_gross": 0.0,
    "price": 27.0,
    "error": false
  },
  {
    "id": 399502,
    "cinemaId": "1012",
    "movieId": "HO00007763",
    "date": "2025-09-14T12:10:00",
    "typeId": "LUX",
    "screenName": "HOYTS LUX 01",
    "operator": "BOTLP",
    "total": 72,
    "sold": 0,
    "available": 72,
    "occupancy": 0.0,
    "max_gross": 1944.0,
    "total_gross": 0.0,
    "price": 27.0,
    "error": false
  },
  {
    "id": 168791,
    "cinemaId": "HAMCIN",
    "movieId": "HO00008135",
    "date": "2025-09-14T14:30:00",
    "typeId": "STANDARD",
    "screenName": "METRO 1",
    "operator": "HAM",
    "total": 126,
    "sold": 0,
    "available": 126,
    "occupancy": 0.0,
    "max_gross": 3402.0,
    "total_gross": 0.0,
    "price": 27.0,
    "error": false
  },
  {
    "id": 399509,
    "cinemaId": "1012",
    "movieId": "HO00007763",
    "date": "2025-09-14T13:40:00",
    "typeId": "LUX",
    "screenName": "HOYTS LUX 02",
    "operator": "BOTLP",
    "total": 38,
    "sold": 2,
    "available": 36,
    "occupancy": 5.26,
    "max_gross": 1026.0,
    "total_gross": 54.0,
    "price": 27.0,
    "error": false
  },
  {
    "id": 399506,
    "cinemaId": "1012",
    "movieId": "HO00007763",
    "date": "2025-09-14T18:20:00",
    "typeId": "LUX",
    "screenName": "HOYTS LUX 02",
    "operator": "BOTLP",
    "total": 38,
    "sold": 0,
    "available": 38,
    "occupancy": 0.0,
    "max_gross": 1026.0,
    "total_gross": 0.0,
    "price": 27.0,
    "error": false
  },
  {
    "id": 399504,
    "cinemaId": "1012",
    "movieId": "HO00007763",
    "date": "2025-09-14T16:00:00",
    "typeId": "LUX",
    "screenName": "HOYTS LUX 02",
    "operator": "BOTLP",
    "total": 38,
    "sold": 0,
    "available": 38,
    "occupancy": 0.0,
    "max_gross": 1026.0,
    "total_gross": 0.0,
    "price": 27.0,
    "error": false
  },
  {
    "id": 168798,
    "cinemaId": "HAMCIN",
    "movieId": "HO00007763",
    "date": "2025-09-14T15:30:00",
    "typeId": "STANDARD",
    "screenName": "METRO 3",
    "operator": "HAM",
    "total": 209,
    "sold": 0,
    "available": 209,
    "occupancy": 0.0,
    "max_gross": 5643.0,
    "total_gross": 0.0,
    "price": 27.0,
    "error": false
  },
  {
    "id": 399505,
    "cinemaId": "1012",
    "movieId": "HO00007763",
    "date": "2025-09-14T16:00:00",
    "typeId": "STANDARD",
    "screenName": "Cinema 2",
    "operator": "BOT",
    "total": 172,
    "sold": 0,
    "available": 172,
    "occupancy": 0.0,
    "max_gross": 4644.0,
    "total_gross": 0.0,
    "price": 27.0,
    "error": false
  },
  {
    "id": 168182,
    "cinemaId": "HAMCIN",
    "movieId": "HO00007812",
    "date": "2025-09-14T16:00:00",
    "typeId": "STANDARD",
    "screenName": "METRO 2",
    "operator": "HAM",
    "total": 126,
    "sold": 6,
    "available": 120,
    "occupancy": 4.76,
    "max_gross": 2898.0,
    "total_gross": 138.0,
    "price": 23.0,
    "error": false
  },
  {
    "id": 168796,
    "cinemaId": "HAMCIN",
    "movieId": "HO00007763",
    "date": "2025-09-14T10:30:00",
    "typeId": "STANDARD",
    "screenName": "METRO 3",
    "operator": "HAM",
    "total": 209,
    "sold": 0,
    "available": 209,
    "occupancy": 0.0,
    "max_gross": 5643.0,
    "total_gross": 0.0,
    "price": 27.0,
    "error": false
  },
  {
    "id": 399922,
    "cinemaId": "1012",
    "movieId": "HO00008135",
    "date": "2025-09-14T10:40:00",
    "typeId": "STANDARD",
    "screenName": "Cinema 5",
    "operator": "BOT",
    "total": 128,
    "sold": 0,
    "available": 128,
    "occupancy": 0.0,
    "max_gross": 3456.0,
    "total_gross": 0.0,
    "price": 27.0,
    "error": false
  },
  {
    "id": 398703,
    "cinemaId": "1012",
    "movieId": "HO00007811",
    "date": "2025-09-14T18:00:00",
    "typeId": "LUX",
    "screenName": "HOYTS LUX 01",
    "operator": "BOTLP",
    "total": 72,
    "sold": 7,
    "available": 65,
    "occupancy": 9.72,
    "max_gross": 1944.0,
    "total_gross": 189.0,
    "price": 27.0,
    "error": false
  },
  {
    "id": 168797,
    "cinemaId": "HAMCIN",
    "movieId": "HO00007763",
    "date": "2025-09-14T13:00:00",
    "typeId": "STANDARD",
    "screenName": "METRO 3",
    "operator": "HAM",
    "total": 209,
    "sold": 0,
    "available": 209,
    "occupancy": 0.0,
    "max_gross": 5643.0,
    "total_gross": 0.0,
    "price": 27.0,
    "error": false
  },
  {
    "id": 194686,
    "cinemaId": "1011",
    "movieId": "HO00007763",
    "date": "2025-09-14T10:30:00",
    "typeId": "STANDARD",
    "screenName": "Cinema 3",
    "operator": "HIB",
    "total": 192,
    "sold": 0,
    "available": 192,
    "occupancy": 0.0,
    "max_gross": 5184.0,
    "total_gross": 0.0,
    "price": 27.0,
    "error": false
  },
  {
    "id": 194688,
    "cinemaId": "1011",
    "movieId": "HO00007763",
    "date": "2025-09-14T14:40:00",
    "typeId": "STANDARD",
    "screenName": "Cinema 3",
    "operator": "HIB",
    "total": 192,
    "sold": 0,
    "available": 192,
    "occupancy": 0.0,
    "max_gross": 5184.0,
    "total_gross": 0.0,
    "price": 27.0,
    "error": false,
    "last_error": "HTTP 500"
  },
  {
    "id": 194687,
    "cinemaId": "1011",
    "movieId": "HO00007763",
    "date": "2025-09-14T12:20:00",
    "typeId": "STANDARD",
    "screenName": "Cinema 3",
    "operator": "HIB",
    "total": 192,
    "sold": 0,
    "available": 192,
    "occupancy": 0.0,
    "max_gross": 5184.0,
    "total_gross": 0.0,
    "price": 27.0,
    "error": false
  },
  {
    "id": 194689,
    "cinemaId": "1011",
    "movieId": "HO00007763",
    "date": "2025-09-14T17:00:00",
    "typeId": "STANDARD",
    "screenName": "Cinema 3",
    "operator": "HIB",
    "total": 192,
    "sold": 0,
    "available": 192,
    "occupancy": 0.0,
    "max_gross": 5184.0,
    "total_gross": 0.0,
    "price": 27.0,
    "error": false
  },
  {
    "id": 194329,
    "cinemaId": "1011",
    "movieId": "HO00007811",
    "date": "2025-09-14T18:00:00",
    "typeId": "STANDARD",
    "screenName": "Cinema 1",
    "operator": "HIB",
    "total": 126,
    "sold": 0,
    "available": 126,
    "occupancy": 0.0,
    "max_gross": 2268.0,
    "total_gross": 0.0,
    "price": 18.0,
    "error": false
  },
  {
    "id": 316029,
    "cinemaId": "1005",
    "movieId": "HO00008135",
    "date": "2025-09-14T14:30:00",
    "typeId": "STANDARD",
    "screenName": "Cinema 2",
    "operator": "RIC",
    "total": 200,
    "sold": 0,
    "available": 200,
    "occupancy": 0.0,
    "max_gross": 5400.0,
    "total_gross": 0.0,
    "price": 27.0,
    "error": false
  },
  {
    "id": 316027,
    "cinemaId": "1005",
    "movieId": "HO00007763",
    "date": "2025-09-14T12:40:00",
    "typeId": "XTREME",
    "screenName": "Xtremescreen 5",
    "operator": "RIC",
    "total": 780,
    "sold": 0,
    "available": 780,
    "occupancy": 0.0,
    "max_gross": 21060.0,
    "total_gross": 0.0,
    "price": 27.0,
    "error": false
  },
  {
    "id": 316026,
    "cinemaId": "1005",
    "movieId": "HO00007763",
    "date": "2025-09-14T10:00:00",
    "typeId": "XTREME",
    "screenName": "Xtremescreen 5",
    "operator": "RIC",
    "total": 780,
    "sold": 0,
    "available": 780,
    "occupancy": 0.0,
    "max_gross": 21060.0,
    "total_gross": 0.0,
    "price": 27.0,
    "error": false
  },
  {
    "id": 316028,
    "cinemaId": "1005",
    "movieId": "HO00007763",
    "date": "2025-09-14T15:20:00",
    "typeId": "XTREME",
    "screenName": "Xtremescreen 5",
    "operator": "RIC",
    "total": 780,
    "sold": 0,
    "available": 780,
    "occupancy": 0.0,
    "max_gross": 21060.0,
    "total_gross": 0.0,
    "price": 27.0,
    "error": false
  },
  {
    "id": 315510,
    "cinemaId": "1005",
    "movieId": "HO00007811",
    "date": "2025-09-14T18:00:00",
    "typeId": "XTREME",
    "screenName": "Xtremescreen 5",
    "operator": "RIC",
    "total": 780,
    "sold": 27,
    "available": 753,
    "occupancy": 3.46,
    "max_gross": 17940.0,
    "total_gross": 621.0,
    "price": 23.0,
    "error": false
  },
  {
    "id": 315509,
    "cinemaId": "1005",
    "movieId": "HO00007812",
    "date": "2025-09-14T16:00:00",
    "typeId": "STANDARD",
    "screenName": "Cinema 6",
    "operator": "RIC",
    "total": 476,
    "sold": 9,
    "available": 467,
    "occupancy": 1.89,
    "max_gross": 8806.0,
    "total_gross": 166.5,
    "price": 18.5,
    "error": false
  },
  {
    "id": 67910,
    "cinemaId": "ORMCIN",
    "movieId": "HO00007763",
    "date": "2025-09-14T13:30:00",
    "typeId": "XTREME",
    "screenName": "Xtremescreen 01",
    "operator": "ORM",
    "total": 286,
    "sold": 0,
    "available": 286,
    "occupancy": 0.0,
    "max_gross": 7722.0,
    "total_gross": 0.0,
    "price": 27.0,
    "error": false
  },
  {
    "id": 67911,
    "cinemaId": "ORMCIN",
    "movieId": "HO00007763",
    "date": "2025-09-14T15:50:00",
    "typeId": "XTREME",
    "screenName": "Xtremescreen 01",
    "operator": "ORM",
    "total": 286,
    "sold": 0,
    "available": 286,
    "occupancy": 0.0,
    "max_gross": 7722.0,
    "total_gross": 0.0,
    "price": 27.0,
    "error": false
  },
  {
    "id": 67907,
    "cinemaId": "ORMCIN",
    "movieId": "HO00007763",
    "date": "2025-09-14T12:20:00",
    "typeId": "STANDARD",
    "screenName": "Cinema 04",
    "operator": "ORM",
    "total": 133,
    "sold": 0,
    "available": 133,
    "occupancy": 0.0,
    "max_gross": 3591.0,
    "total_gross": 0.0,
    "price": 27.0,
    "error": false
  },
  {
    "id": 67909,
    "cinemaId": "ORMCIN",
    "movieId": "HO00007763",
    "date": "2025-09-14T11:10:00",
    "typeId": "XTREME",
    "screenName": "Xtremescreen 01",
    "operator": "ORM",
    "total": 286,
    "sold": 0,
    "available": 286,
    "occupancy": 0.0,
    "max_gross": 7722.0,
    "total_gross": 0.0,
    "price": 27.0,
    "error": false
  },
  {
    "id": 67908,
    "cinemaId": "ORMCIN",
    "movieId": "HO00007763",
    "date": "2025-09-14T10:00:00",
    "typeId": "STANDARD",
    "screenName": "Cinema 04",
    "operator": "ORM",
    "total": 133,
    "sold": 0,
    "available": 133,
    "occupancy": 0.0,
    "max_gross": 3591.0,
    "total_gross": 0.0,
    "price": 27.0,
    "error": false
  },
  {
    "id": 68314,
    "cinemaId": "ORMCIN",
    "movieId": "HO00007763",
    "date": "2025-09-14T12:00:00",
    "typeId": "XTREME",
    "screenName": "Xtremescreen 07",
    "operator": "ORM",
    "total": 176,
    "sold": 0,
    "available": 176,
    "occupancy": 0.0,
    "max_gross": 4752.0,
    "total_gross": 0.0,
    "price": 27.0,
    "error": false
  },
  {
    "id": 68313,
    "cinemaId": "ORMCIN",
    "movieId": "HO00007763",
    "date": "2025-09-14T13:10:00",
    "typeId": "XTREME",
    "screenName": "Xtremescreen 01",
    "operator": "ORM",
    "total": 286,
    "sold": 0,
    "available": 286,
    "occupancy": 0.0,
    "max_gross": 7722.0,
    "total_gross": 0.0,
    "price": 27.0,
    "error": false
  },
  {
    "id": 68316,
    "cinemaId": "ORMCIN",
    "movieId": "HO00007763",
    "date": "2025-09-14T09:30:00",
    "typeId": "XTREME",
    "screenName": "Xtremescreen 07",
    "operator": "ORM",
    "total": 176,
    "sold": 0,
    "available": 176,
    "occupancy": 0.0,
    "max_gross": 4752.0,
    "total_gross": 0.0,
    "price": 27.0,
    "error": false
  },
  {
    "id": 68317,
    "cinemaId": "ORMCIN",
    "movieId": "HO00007763",
    "date": "2025-09-14T15:40:00",
    "typeId": "XTREME",
    "screenName": "Xtremescreen 01",
    "operator": "ORM",
    "total": 286,
    "sold": 0,
    "available": 286,
    "occupancy": 0.0,
    "max_gross": 7722.0,
    "total_gross": 0.0,
    "price": 27.0,
    "error": false
  },
  {
    "id": 68315,
    "cinemaId": "ORMCIN",
    "movieId": "HO00007763",
    "date": "2025-09-14T10:40:00",
    "typeId": "XTREME",
    "screenName": "Xtremescreen 01",
    "operator": "ORM",
    "total": 286,
    "sold": 0,
    "available": 286,
    "occupancy": 0.0,
    "max_gross": 7722.0,
    "total_gross": 0.0,
    "price": 27.0,
    "error": false
  }
]